Mini_Exchange-0.0.8.dist-info/DESCRIPTION.rst
Mini_Exchange-0.0.8.dist-info/METADATA
Mini_Exchange-0.0.8.dist-info/RECORD
Mini_Exchange-0.0.8.dist-info/WHEEL
Mini_Exchange-0.0.8.dist-info/metadata.json
Mini_Exchange-0.0.8.dist-info/top_level.txt
mini_exchange/Strategy.py
mini_exchange/Trading_system.py
mini_exchange/__init__.py
mini_exchange/change_index.py
mini_exchange/cprint.py
