Metadata-Version: 2.0
Name: Mini-Exchange
Version: 0.0.8
Summary: Time based strategy back testing system
Home-page: UNKNOWN
Author: Yili Peng
Author-email: yili_peng@outlook.com
License: UNKNOWN
Keywords: quant
Platform: UNKNOWN
Requires-Dist: plotly
